pixelproject/__init__.py
pixelproject/collections.py
pixelproject/grid.py
pixelproject/tools.py
pixelproject-0.2.0.dist-info/LICENSE
pixelproject-0.2.0.dist-info/METADATA
pixelproject-0.2.0.dist-info/WHEEL
pixelproject-0.2.0.dist-info/top_level.txt
pixelproject-0.2.0.dist-info/RECORD
