Metadata-Version: 2.1
Name: pixelproject
Version: 0.2.0
Summary: pixelproject
Home-page: https://github.com/MickaelRigault/pixelproject/
Download-URL: https://github.com/MickaelRigault/pixelproject/tarball/0.2
Author: Mickael Rigault
Author-email: m.rigault@ipnl.in2p3.fr
Maintainer: Mickael Rigault
Maintainer-email: m.rigault@ipnl.in2p3.fr
License: Apache 2.0
Classifier: Intended Audience :: Science/Research
Classifier: Programming Language :: Python :: 2.7
Classifier: Programming Language :: Python :: 3.5
Classifier: License :: OSI Approved :: BSD License
Classifier: Topic :: Scientific/Engineering :: Astronomy
Classifier: Operating System :: POSIX
Classifier: Operating System :: Unix
Classifier: Operating System :: MacOS
License-File: LICENSE
Requires-Dist: propobject
Requires-Dist: shapely
Requires-Dist: geopandas
